{
    "configurations": [
        {
            "name": "Win32",
            "includePath": [
                "${workspaceFolder}/**",
                "${workspaceFolder}/depends/SDL2-VC/include",
                "${workspaceFolder}/depends/SDL2-mingw/include"
            ],
            "defines": [
                "_DEBUG",
                "UNICODE",
                "_UNICODE"
            ],
            "cppStandard": "c++20",
            "intelliSenseMode": "windows-gcc-x64",
            "configurationProvider": "ms-vscode.makefile-tools",
            "browse": {
                "databaseFilename": "${workspaceFolder}/.vscode/BROWSE.VC.DB"
            }
        }
    ],
    "version": 4
}